COPYING
setup.cfg
setup.py
LinkExchange.Zope.egg-info/PKG-INFO
LinkExchange.Zope.egg-info/SOURCES.txt
LinkExchange.Zope.egg-info/dependency_links.txt
LinkExchange.Zope.egg-info/namespace_packages.txt
LinkExchange.Zope.egg-info/requires.txt
LinkExchange.Zope.egg-info/top_level.txt
linkexchange/__init__.py
linkexchange/zope/__init__.py
linkexchange/zope/configure.zcml
linkexchange/zope/support.py
linkexchange/zope/Extensions/Method.py
linkexchange/zope/Extensions/__init__.py