Metadata-Version: 1.0
Name: LinkExchange.Zope
Version: 0.1
Summary: Zope integration with LinkExchange library
Home-page: http://linkexchange.org.ua
Author: Konstantin Korikov
Author-email: lostclus@gmail.com
License: LGPL
Download-URL: http://linkexchange.org.ua/downloads
Platform: UNKNOWN
Classifier: Development Status :: 4 - Beta
Classifier: Environment :: Web Environment
Classifier: Framework :: Zope2
Classifier: Intended Audience :: Developers
Classifier: Intended Audience :: System Administrators
Classifier: License :: OSI Approved :: GNU Library or Lesser General Public License (LGPL)
Classifier: Operating System :: OS Independent
Classifier: Programming Language :: Python :: 2
Classifier: Topic :: Internet :: WWW/HTTP :: Dynamic Content
